<ModOps>
    
    <!-- Distribute researchpoints via RewardConfig seems not to work unfortunately... -->
    
    <!-- <ModOp Type="replace" Name='A7_QuestDeliveryObject' Path="//Template/Properties/Reward"> -->
	  <!-- <Reward> -->
        <!-- <RewardAssets> -->
          <!-- <Item> -->
            <!-- <VectorElement> -->
              <!-- <InheritedIndex>0</InheritedIndex> -->
            <!-- </VectorElement> -->
          <!-- </Item> -->
          <!-- <Item> -->
            <!-- <VectorElement> -->
              <!-- <InheritedIndex>1</InheritedIndex> -->
            <!-- </VectorElement> -->
            <!-- <Reward>0</Reward> -->
          <!-- </Item> -->
          <!-- <Item> -->
            <!-- <VectorElement> -->
              <!-- <InheritedIndex>2</InheritedIndex> -->
            <!-- </VectorElement> -->
            <!-- <Reward>0</Reward> -->
          <!-- </Item> -->
        <!-- </RewardAssets> -->
        <!-- <RewardReputation> -->
          <!-- <Item> -->
            <!-- <ReputationAmount>3</ReputationAmount> -->
          <!-- </Item> -->
        <!-- </RewardReputation> -->
      <!-- </Reward> -->
	<!-- </ModOp> -->
    
    
    <!-- <ModOp Type="replace" Name='A7_QuestPickupObject' Path="//Template/Properties/Reward"> -->
	  <!-- <Reward> -->
        <!-- <RewardAssets> -->
          <!-- <Item> -->
            <!-- <VectorElement> -->
              <!-- <InheritedIndex>0</InheritedIndex> -->
            <!-- </VectorElement> -->
          <!-- </Item> -->
          <!-- <Item> -->
            <!-- <VectorElement> -->
              <!-- <InheritedIndex>1</InheritedIndex> -->
            <!-- </VectorElement> -->
            <!-- <Reward>0</Reward> -->
          <!-- </Item> -->
          <!-- <Item> -->
            <!-- <VectorElement> -->
              <!-- <InheritedIndex>2</InheritedIndex> -->
            <!-- </VectorElement> -->
            <!-- <Reward>0</Reward> -->
          <!-- </Item> -->
        <!-- </RewardAssets> -->
        <!-- <RewardReputation> -->
          <!-- <Item> -->
            <!-- <ReputationAmount>3</ReputationAmount> -->
          <!-- </Item> -->
        <!-- </RewardReputation> -->
      <!-- </Reward> -->
	<!-- </ModOp> -->
    
</ModOps>