<ModOps>

  
  
  <ModOp Type="AddNextSibling" GUID="700047">
    <Asset>
      <Template>AssetPool</Template>
      <Values>
        <Standard>
          <GUID>1500001475</GUID>
          <Name>all culture buildings 193666</Name>
        </Standard>
        <AssetPool>
          <AssetList />
        </AssetPool>
      </Values>
    </Asset>
  </ModOp>
  <ModOp Type="merge" Path="@1500001475/AssetPool/AssetList"
    Content="@193666/ItemEffectTargetPool/EffectTargetGUIDs/Item/GUID/text()">
    <Item>
      <Asset>
        <ModOpContent />
      </Asset>
    </Item>
  </ModOp>
  
  
  
  

</ModOps>