<ModOps>
  
  <!-- translation needed: -->
  
  
  <!-- hint that the failure of the expedition is intended and you did nothing wrong -->
  <ModOp Type="add" Path="/TextExport/Texts/Text[GUID='104086']/Text">&lt;br/&gt;(best possible outcome)</ModOp>
  
  <ModOp Type="add" Path="/TextExport/Texts/Text[GUID='1395']/Text"> (Questline)</ModOp>
  
  <!-- hint that you have to own an airship near the missing sister object -->
  <ModOp Path="/TextExport/Texts" Type="add">
    <Text>
      <GUID>1500004381</GUID>
      <Text>An Airship has to fly nearby the missing sister.</Text>
    </Text>
    <!-- Reproduction of the penguin (10745) named Quinn -->
    <Text>
      <GUID>1500004411</GUID>
      <Text>Reproduction [AssetData(10745) Text] Quinn</Text>
    </Text>
  </ModOp>
  
  
  
  <!-- #################################################################################### -->
  
  <!-- no translation needed: -->

  <!-- add info that you need to do expedition with airship -->
   <ModOp Type="add" Path="/TextExport/Texts/Text[GUID='103946']/Text" Content="/TextExport/Texts/Text[GUID = '116566']/Text/text()">&lt;br/&gt;(<ModOpContent />)</ModOp>

  
  <!-- correct text for Pool 104456 that it allows 1060 and 1737 -->
  <ModOp Type="replace" Path="/TextExport/Texts/Text[GUID='104456']/Text">
    <Text>[AssetData(1060) Text] / [AssetData(1737) Text]</Text>
  </ModOp>
   
  
</ModOps>