<ModOps>
    
    <!-- verwendet Serp GUIDs von 1500001021 bis einschließlich 1500001024 -->
    
    <!-- Neue Kategorien -->
    <ModOp Type="AddNextSibling" GUID="2288">
        <Asset>
          <Template>Text</Template>
          <Values>
            <Standard>
              <GUID>1500001021</GUID>
              <Name>OldWorld Category</Name>
              <IconFilename>data/modgraphics/icons/icon_session_moderate_dark_3.png</IconFilename>
            </Standard>
          </Values>
        </Asset>
    </ModOp>
    <ModOp Type="AddNextSibling" GUID="2288">
        <Asset>
          <Template>Text</Template>
          <Values>
            <Standard>
              <GUID>1500001022</GUID>
              <Name>NewWorld Category</Name>
              <IconFilename>data/modgraphics/icons/icon_session_southamerica_dark_3.png</IconFilename>
            </Standard>
          </Values>
        </Asset>
    </ModOp>
    <ModOp Type="AddNextSibling" GUID="2288">
        <Asset>
          <Template>Text</Template>
          <Values>
            <Standard>
              <GUID>1500001023</GUID>
              <Name>Artic Category</Name>
              <IconFilename>data/modgraphics/icons/icon_session_passage_dark_3.png</IconFilename>
            </Standard>
          </Values>
        </Asset>
    </ModOp>
    <ModOp Type="AddNextSibling" GUID="2288">
        <Asset>
          <Template>Text</Template>
          <Values>
            <Standard>
              <GUID>1500001024</GUID>
              <Name>Enbesa Category</Name>
              <IconFilename>data/modgraphics/icons/icon_session_landoflions_dark_3.png</IconFilename>
            </Standard>
          </Values>
        </Asset>
    </ModOp>
    
    <!-- BonusNeeds sorted into categories -->
    <ModOp Type="replace" GUID="25000118" Path="/Values/ObjectmenuResidenceScene/BonusNeeds/BonusNeeds">
        <BonusNeeds>
          <Item>
            <!-- <Category>2288</Category> -->
            <Category>1500001021</Category>
            <Needs>
              <Item>
                <BonusNeed>114425</BonusNeed>
              </Item>
              <Item>
                <BonusNeed>114431</BonusNeed>
              </Item>
              <Item>
                <BonusNeed>535</BonusNeed>
              </Item>
              <Item>
                <BonusNeed>536</BonusNeed>
              </Item>
              <Item>
                <BonusNeed>2524</BonusNeed>
              </Item>
            </Needs>
          </Item>
          <Item>
            <!-- <Category>2289</Category> -->
            <Category>1500001022</Category>
            <Needs>
              <Item>
                <BonusNeed>1010235</BonusNeed>
              </Item>
              <Item>
                <BonusNeed>1010239</BonusNeed>
              </Item>
              <Item>
                <BonusNeed>1010213</BonusNeed>
              </Item>
              <Item>
                <BonusNeed>1010257</BonusNeed>
              </Item>
              <Item>
                <BonusNeed>25506</BonusNeed>
              </Item>
              <Item>
                <BonusNeed>1010258</BonusNeed>
              </Item>
              <Item>
                <BonusNeed>133183</BonusNeed>
              </Item>
              <Item>
                <BonusNeed>1010234</BonusNeed>
              </Item>
              <Item>
                <BonusNeed>5382</BonusNeed>
              </Item>
              <Item>
                <BonusNeed>1010193</BonusNeed>
              </Item>
              <Item>
                <BonusNeed>6600</BonusNeed>
              </Item>
              <Item>
                <BonusNeed>1010217</BonusNeed>
              </Item>
            </Needs>
          </Item>
          <Item>
            <!-- <Category>2290</Category> -->
            <Category>1500001023</Category>
            <Needs>
              <Item>
                <BonusNeed>1010203</BonusNeed>
              </Item>
              <Item>
                <BonusNeed>135109</BonusNeed>
              </Item>
              <Item>
                <BonusNeed>120042</BonusNeed>
              </Item>
              <Item>
                <BonusNeed>112699</BonusNeed>
              </Item>
              <Item>
                <BonusNeed>133181</BonusNeed>
              </Item>
              <Item>
                <BonusNeed>5397</BonusNeed>
              </Item>
              <Item>
                <BonusNeed>5383</BonusNeed>
              </Item>
              <Item>
                <BonusNeed>5386</BonusNeed>
              </Item>
              <Item>
                <BonusNeed>114364</BonusNeed>
              </Item>
            </Needs>
          </Item>
          <Item>
            <!-- <Category>2361</Category> -->
            <Category>1500001024</Category>
            <Needs>
              <Item>
                <BonusNeed>1010356</BonusNeed>
              </Item>
              <Item>
                <BonusNeed>135107</BonusNeed>
              </Item>
              <Item>
                <BonusNeed>135108</BonusNeed>
              </Item>
              <Item>
                <BonusNeed>1010250</BonusNeed>
              </Item>
              <Item>
                <BonusNeed>114430</BonusNeed>
              </Item>
              <Item>
                <BonusNeed>114428</BonusNeed>
              </Item>
              <Item>
                <BonusNeed>1010209</BonusNeed>
              </Item>
              <Item>
                <BonusNeed>112695</BonusNeed>
              </Item>
              <Item>
                <BonusNeed>114404</BonusNeed>
              </Item>
              <Item>
                <BonusNeed>120037</BonusNeed>
              </Item>
              <Item>
                <BonusNeed>1010208</BonusNeed>
              </Item>
              <Item>
                <BonusNeed>117699</BonusNeed>
              </Item>
            </Needs>
          </Item>
          <Item>
            <Category>4275</Category>
            <Needs>
              <Item>
                <BonusNeed>1010232</BonusNeed>
              </Item>
              <Item>
                <BonusNeed>4267</BonusNeed>
              </Item>
              <Item>
                <BonusNeed>4268</BonusNeed>
              </Item>
              <Item>
                <BonusNeed>117698</BonusNeed>
              </Item>
              <Item>
                <BonusNeed>135230</BonusNeed>
              </Item>
              <Item>
                <BonusNeed>120030</BonusNeed>
              </Item>
              <Item>
                <BonusNeed>1010222</BonusNeed>
              </Item>
              <Item>
                <BonusNeed>1010224</BonusNeed>
              </Item>
              <Item>
                <BonusNeed>5390</BonusNeed>
              </Item>
            </Needs>
          </Item>
          <Item>
            <Category>4837</Category>
            <Needs>
              <Item>
                <BonusNeed>1010201</BonusNeed>
              </Item>
              <Item>
                <BonusNeed>1010197</BonusNeed>
              </Item>
              <Item>
                <BonusNeed>117702</BonusNeed>
              </Item>
              <Item>
                <BonusNeed>1010192</BonusNeed>
              </Item>
              <Item>
                <BonusNeed>1010237</BonusNeed>
              </Item>
              <Item>
                <BonusNeed>114365</BonusNeed>
              </Item>
              <Item>
                <BonusNeed>114367</BonusNeed>
              </Item>
              <Item>
                <BonusNeed>114356</BonusNeed>
              </Item>
              <Item>
                <BonusNeed>120034</BonusNeed>
              </Item>
              <Item>
                <BonusNeed>120043</BonusNeed>
              </Item>
              <Item>
                <BonusNeed>112697</BonusNeed>
              </Item>
              <Item>
                <BonusNeed>1010206</BonusNeed>
              </Item>
              <Item>
                <BonusNeed>1010240</BonusNeed>
              </Item>
              <Item>
                <BonusNeed>120044</BonusNeed>
              </Item>
              <Item>
                <BonusNeed>5384</BonusNeed>
              </Item>
              <Item>
                <BonusNeed>5400</BonusNeed>
              </Item>
            </Needs>
          </Item>
          <Item>
            <Category>6364</Category>
            <Needs>
              <Item>
                <BonusNeed>1010245</BonusNeed>
              </Item>
              <Item>
                <BonusNeed>1010248</BonusNeed>
              </Item>
              <Item>
                <BonusNeed>6265</BonusNeed>
              </Item>
              <Item>
                <BonusNeed>5830</BonusNeed>
              </Item>
              <Item>
                <BonusNeed>5831</BonusNeed>
              </Item>
              <Item>
                <BonusNeed>5803</BonusNeed>
              </Item>
              <Item>
                <BonusNeed>5391</BonusNeed>
              </Item>
              <Item>
                <BonusNeed>120016</BonusNeed>
              </Item>
              <Item>
                <BonusNeed>135232</BonusNeed>
              </Item>
              <Item>
                <BonusNeed>114414</BonusNeed>
              </Item>
              <Item>
                <BonusNeed>5388</BonusNeed>
              </Item>
              <Item>
                <BonusNeed>5392</BonusNeed>
              </Item>
              <Item>
                <BonusNeed>5395</BonusNeed>
              </Item>
              <Item>
                <BonusNeed>133532</BonusNeed>
              </Item>
            </Needs>
          </Item>
        </BonusNeeds>
    </ModOp>

    <!-- Bauern -->

    <ModOp Type="replace" GUID="15000000" Path="/Values/PopulationLevel7/PopulationInputs">
      <PopulationInputs>
        <Item>
          <Product>120020</Product>
          <SupplyWeight>5</SupplyWeight>
          <IsConsideredByAI>1</IsConsideredByAI>
        </Item>
        <Item>
          <Product>1010200</Product>
          <Amount>0.0004166667</Amount>
          <SupplyWeight>3</SupplyWeight>
          <MoneyValue>10</MoneyValue>
          <FullWeightPopulationCount>100</FullWeightPopulationCount>
          <NoWeightPopulationCount>49</NoWeightPopulationCount>
          <IsConsideredByAI>1</IsConsideredByAI>
        </Item>
        <Item>
          <Product>1010216</Product>
          <Amount>0.000555556</Amount>
          <HappinessValue>8</HappinessValue>
          <MoneyValue>30</MoneyValue>
          <FullWeightPopulationCount>150</FullWeightPopulationCount>
          <NoWeightPopulationCount>99</NoWeightPopulationCount>
          <IsConsideredByAI>1</IsConsideredByAI>
        </Item>
        <Item>
          <Product>1010237</Product>
          <Amount>0.000512821</Amount>
          <SupplyWeight>2</SupplyWeight>
          <MoneyValue>30</MoneyValue>
          <FullWeightPopulationCount>150</FullWeightPopulationCount>
          <NoWeightPopulationCount>99</NoWeightPopulationCount>
          <IsConsideredByAI>1</IsConsideredByAI>
        </Item>
        <Item>
          <Product>1010349</Product>
          <HappinessValue>12</HappinessValue>
          <MoneyValue>12</MoneyValue>
          <FullWeightPopulationCount>150</FullWeightPopulationCount>
          <NoWeightPopulationCount>149</NoWeightPopulationCount>
          <IsConsideredByAI>1</IsConsideredByAI>
        </Item>
        <Item>
          <Product>1010235</Product>
          <Amount>0.0004</Amount>
          <SupplyWeight>1</SupplyWeight>
          <MoneyValue>6</MoneyValue>
          <AdditionalGlobalUnlockRequirement>
            <Population>15000001</Population>
            <MinPopulationAmount>150</MinPopulationAmount>
          </AdditionalGlobalUnlockRequirement>
          <ExcludePopulationFromMoneyAndConsumptionCalculation>1</ExcludePopulationFromMoneyAndConsumptionCalculation>
          <IsBonusNeed>1</IsBonusNeed>
        </Item>
        <Item>
          <Product>1010239</Product>
          <Amount>0.0002</Amount>
          <SupplyWeight>1</SupplyWeight>
          <MoneyValue>19</MoneyValue>
          <AdditionalGlobalUnlockRequirement>
            <Population>15000002</Population>
            <MinPopulationAmount>500</MinPopulationAmount>
          </AdditionalGlobalUnlockRequirement>
          <ExcludePopulationFromMoneyAndConsumptionCalculation>1</ExcludePopulationFromMoneyAndConsumptionCalculation>
          <IsBonusNeed>1</IsBonusNeed>
        </Item>
        <Item>
          <Product>133183</Product>
          <Amount>0.0003333333</Amount>
          <SupplyWeight>2</SupplyWeight>
          <MoneyValue>12</MoneyValue>
          <AdditionalGlobalUnlockRequirement>
            <Population>601379</Population>
            <MinPopulationAmount>300</MinPopulationAmount>
          </AdditionalGlobalUnlockRequirement>
          <ExcludePopulationFromMoneyAndConsumptionCalculation>1</ExcludePopulationFromMoneyAndConsumptionCalculation>
          <IsBonusNeed>1</IsBonusNeed>
        </Item>
        <Item>
          <Product>535</Product>
          <Amount>0.000266667</Amount>
          <SupplyWeight>1</SupplyWeight>
          <MoneyValue>10</MoneyValue>
          <AdditionalGlobalUnlockRequirement>
            <Population>15000002</Population>
            <MinPopulationAmount>500</MinPopulationAmount>
          </AdditionalGlobalUnlockRequirement>
          <ExcludePopulationFromMoneyAndConsumptionCalculation>1</ExcludePopulationFromMoneyAndConsumptionCalculation>
          <IsBonusNeed>1</IsBonusNeed>
        </Item>
        <Item>
          <Product>536</Product>
          <Amount>0.000133333</Amount>
          <SupplyWeight>1</SupplyWeight>
          <MoneyValue>30</MoneyValue>
          <AdditionalGlobalUnlockRequirement>
            <Population>15000006</Population>
            <MinPopulationAmount>1</MinPopulationAmount>
          </AdditionalGlobalUnlockRequirement>
          <ExcludePopulationFromMoneyAndConsumptionCalculation>1</ExcludePopulationFromMoneyAndConsumptionCalculation>
          <IsBonusNeed>1</IsBonusNeed>
        </Item>
        <Item>
          <Product>2524</Product>
          <Amount>5E-05</Amount>
          <SupplyWeight>3</SupplyWeight>
          <MoneyValue>60</MoneyValue>
          <AdditionalGlobalUnlockRequirement>
            <Population>15000006</Population>
            <MinPopulationAmount>1000</MinPopulationAmount>
          </AdditionalGlobalUnlockRequirement>
          <ExcludePopulationFromMoneyAndConsumptionCalculation>1</ExcludePopulationFromMoneyAndConsumptionCalculation>
          <IsBonusNeed>1</IsBonusNeed>
        </Item>
        <Item>
          <Product>1010203</Product>
          <Amount>5.833333E-05</Amount>
          <SupplyWeight>1</SupplyWeight>
          <MoneyValue>15</MoneyValue>
          <AdditionalGlobalUnlockRequirement>
            <Population>15000001</Population>
            <MinPopulationAmount>300</MinPopulationAmount>
          </AdditionalGlobalUnlockRequirement>
          <ExcludePopulationFromMoneyAndConsumptionCalculation>1</ExcludePopulationFromMoneyAndConsumptionCalculation>
          <IsBonusNeed>1</IsBonusNeed>
        </Item>
        <Item>
          <Product>5383</Product>
          <Amount>0.0002833333</Amount>
          <SupplyWeight>2</SupplyWeight>
          <MoneyValue>45</MoneyValue>
          <AdditionalGlobalUnlockRequirement>
            <Population>5403</Population>
            <MinPopulationAmount>1</MinPopulationAmount>
          </AdditionalGlobalUnlockRequirement>
          <ExcludePopulationFromMoneyAndConsumptionCalculation>1</ExcludePopulationFromMoneyAndConsumptionCalculation>
          <IsBonusNeed>1</IsBonusNeed>
        </Item>
        <Item>
          <Product>114364</Product>
          <Amount>0.0001666667</Amount>
          <SupplyWeight>3</SupplyWeight>
          <MoneyValue>12</MoneyValue>
          <AdditionalGlobalUnlockRequirement>
            <Population>114329</Population>
            <MinPopulationAmount>300</MinPopulationAmount>
          </AdditionalGlobalUnlockRequirement>
          <ExcludePopulationFromMoneyAndConsumptionCalculation>1</ExcludePopulationFromMoneyAndConsumptionCalculation>
          <IsBonusNeed>1</IsBonusNeed>
        </Item>
      </PopulationInputs>
    </ModOp>

  


</ModOps>