{
  "Version": "1.002",
  "ModID": "Sabotage_Serp",
  "IncompatibleIds": null,
  "ModDependencies": ["shared_LuaUltimateHelpers_Serp","WhichPlayer_Serp"],
  "LoadAfterIds": [
    "WIPItems",
    "shared_LuaUltimateHelpers_Serp",
    "WhichPlayer_Serp",
    "military_attention_legendary_ai",
    "[Gameplay] 02 Combat Overhaul AI",
    "[Gameplay] 02 Combat Overhaul AI ",
    "[Gameplay] 02 Combat Overhaul AI  ",
    "[Gameplay] 02 Combat Overhaul AI   ",
    "[Gameplay] 02 Combat Overhaul AI    ",
    "[Gameplay] 02 Combat Overhaul AI     ",
    "[Gameplay] 02 Combat Overhaul AI Easy",
    "[Gameplay] 02 Combat Overhaul AI Medium",
    "[Gameplay] 02 Combat Overhaul AI Hard"
  ],
  "Category": {
    "English": "Gameplay"
  },
  "ModName": {
    "English": "Sabotage",
    "German": "Sabotage"
  },
  "Description": {
    "English": "Sabotage",
    "German": "Sabotage"
  },
  "KnownIssues": [
    {
      "English": null
    }
  ],
  "DLCDependencies": null,
  "CreatorName": "Serp",
  "CreatorContact": "https://github.com/Serpens66"
}